MANIFEST.in
README.rst
setup.py
Stego.egg-info/PKG-INFO
Stego.egg-info/SOURCES.txt
Stego.egg-info/dependency_links.txt
Stego.egg-info/requires.txt
Stego.egg-info/top_level.txt
bin/stegd
bin/stege
stego/__init__.py
stego/stegd.py
stego/stege.py
stego/utility.py