Metadata-Version: 1.1
Name: Stego
Version: 0.0.2
Summary: <function readme at 0x100756f28>
Home-page: https://github.com/jimmyou587/stegno
Author: Linqiang Ouyang (Jimmy)
Author-email: jimmyou587@gmail.com
License: MIT
Keywords: python,steganography
Platform: UNKNOWN
Classifier: Development Status :: 3 - Alpha
Classifier: Intended Audience :: Developers
Classifier: License :: OSI Approved :: MIT License
Classifier: Programming Language :: Python :: 2
Classifier: Programming Language :: Python :: 2.6
Classifier: Programming Language :: Python :: 2.7
Classifier: Programming Language :: Python :: 3
Classifier: Programming Language :: Python :: 3.3
Classifier: Programming Language :: Python :: 3.4
Classifier: Programming Language :: Python :: 3.5
